piig/Makefile
piig/__init__.py
piig/__main__.py
piig/_version.py
piig/axis.py
piig/compile.py
piig/coords.py
piig/csearch.py
piig/deb.py
piig/doc/haas.txt
piig/examples/defs.py
piig/examples/vicecenter.nc
piig/examples/vicecenter.py
piig/exception.py
piig/fio.py
piig/fortest.py
piig/function.py
piig/g.py
piig/gbl.py
piig/goto.py
piig/gtype.py
piig/haas.py
piig/iface.py
piig/interp.py
piig/ity.py
piig/lib.py
piig/main.py
piig/makestdvars.py
piig/mvarsorig
piig/nd.py
piig/op.py
piig/ptest.py
piig/sac.py
piig/sandl.py
piig/support.py
piig/tests/conftest.py
piig/tests/golden/bad_attribute.nc
piig/tests/golden/bad_bounds0.nc
piig/tests/golden/bad_bounds1.nc
piig/tests/golden/basic_folding0.nc
piig/tests/golden/basic_folding1.nc
piig/tests/golden/conflicting_sizes.nc
piig/tests/golden/const_deref_addresses.nc
piig/tests/golden/constant_arithmetic.nc
piig/tests/golden/coord_addr0.nc
piig/tests/golden/coord_bp.nc
piig/tests/golden/coord_conflicting_sizes.nc
piig/tests/golden/coord_const0.nc
piig/tests/golden/coord_const1.nc
piig/tests/golden/coord_fix_feed.nc
piig/tests/golden/coord_goto.nc
piig/tests/golden/coord_goto_bad_relabs.nc
piig/tests/golden/coord_goto_bad_speeds.nc
piig/tests/golden/coord_goto_bad_speeds0.nc
piig/tests/golden/coord_goto_bad_speeds1.nc
piig/tests/golden/coord_goto_bad_speeds2.nc
piig/tests/golden/coord_goto_rel.nc
piig/tests/golden/coord_kwargs.nc
piig/tests/golden/coord_non_kwargs.nc
piig/tests/golden/coord_overlapping.nc
piig/tests/golden/coord_size0.nc
piig/tests/golden/coord_symtab.nc
piig/tests/golden/coord_symtab1.nc
piig/tests/golden/coord_symtab_n2.nc
piig/tests/golden/kwargs.nc
piig/tests/golden/missing_functions.nc
piig/tests/golden/nesting_functions1.nc
piig/tests/golden/nesting_functions2.nc
piig/tests/golden/nesting_functions3.nc
piig/tests/golden/ok.nc
piig/tests/golden/ok2.nc
piig/tests/golden/operator_precedence.nc
piig/tests/golden/prev_errors.nc
piig/tests/golden/simple_arrays.nc
piig/tests/golden/simple_code0.nc
piig-0.1.50.dist-info/METADATA
piig-0.1.50.dist-info/WHEEL
piig-0.1.50.dist-info/RECORD
